Topsis_Nikhil_101917095.py
Topsis_Nikhil_101917095-0.0.1.dist-info/LICENSE
Topsis_Nikhil_101917095-0.0.1.dist-info/METADATA
Topsis_Nikhil_101917095-0.0.1.dist-info/WHEEL
Topsis_Nikhil_101917095-0.0.1.dist-info/top_level.txt
Topsis_Nikhil_101917095-0.0.1.dist-info/RECORD
