Metadata-Version: 2.1
Name: Topsis-Nikhil-101917095
Version: 0.0.1
Summary: Topsis package by Nikhil 101917095 CSE4
Home-page: UNKNOWN
Author: Nikhil Singla
License: UNKNOWN
Keywords: nikhil singla,tiet,topsis
Platform: UNKNOWN
Classifier: Programming Language :: Python :: 3
Classifier: License :: OSI Approved :: MIT License
Classifier: Operating System :: OS Independent
Requires-Python: >=3.6
Requires-Dist: pandas
